ml_project_tracker/__init__.py
ml_project_tracker/neptune_tools.py
ml_project_tracker/wandb_tools.py
ml_project_tracker-0.0.4.dist-info/METADATA
ml_project_tracker-0.0.4.dist-info/WHEEL
ml_project_tracker-0.0.4.dist-info/top_level.txt
ml_project_tracker-0.0.4.dist-info/RECORD
