Metadata-Version: 2.1
Name: ml-project-tracker
Version: 0.0.4
Summary: A package for tracking the ML projects
Home-page: https://github.com/mahdid-lilia/ML-Project-Tracker
Author: Lilia MAHDID
Author-email: jl_mahdid@esi.dz
Keywords: Deep Learning,Machine Learning,Wandb,Neptune
Classifier: License :: OSI Approved :: MIT License
Classifier: Programming Language :: Python :: 3
Classifier: Operating System :: OS Independent
Requires-Dist: wandb
Requires-Dist: numpy
Requires-Dist: torchvision
Requires-Dist: torch
Requires-Dist: neptune
